gaoya-0.2.0.dist-info/METADATA
gaoya-0.2.0.dist-info/WHEEL
gaoya/simhash.py
gaoya/__init__.py
gaoya/minhash.py
gaoya/gaoya.abi3.so
gaoya-0.2.0.dist-info/RECORD
