Metadata-Version: 2.1
Name: gaoya
Version: 0.2.0
Summary: Locality Sensitive Hashing
Home-Page: https://github.com/serega/gaoya
Author: Sergey Melderis <sergey.melderis@gmail.com>
Author-email: Sergey Melderis <sergey.melderis@gmail.com>
License: MIT
Requires-Python: >=3.7
Project-URL: Source Code, https://github.com/serega/gaoya
